[
    {
        "id": "slide-1",
        "color": "teal",
        "class": "slide",
        "textSize": "large-text",
        "text": "Start at Center , Move to center",
        "textSize2":"small-text",
        "text2": "Fade out at center" ,
        "firstAnimStart":{
            "x": "center" ,
            "y": "center" 
        }, 
        "firstAnimEnd":{
            "x": "center" ,
            "y": "center" 
        }, 
        "secondAnimEnd":{
            "x": "center" ,
            "y": "center" 
        }, 
        "timeToFade":"+=1"
    },
    {
        "id": "slide-2",
        "color": "teal",
        "class": "slide",
        "textSize": "large-text",
        "text": "Start at Start , Move to center",
        "firstAnimStart":{
            "x": 0 ,
            "y": 0 
        }, 
        "firstAnimEnd":{
            "x": "center" ,
            "y": "center" 
        }, 
        "textSize2":"small-text",
        "text2": "Move Y to End " ,
        "secondAnimEnd":{
            "x": "center" ,
            "y": "end" 
        }, 
        "timeToFade":"+=1"
    },
    {
        "id": "slide-3",
        "color": "teal",
        "class": "slide",
        "textSize": "large-text",
        "text": "Start at Center. Move to center",
        "firstAnimStart":{
            "x": "center" ,
            "y": "center" 
        }, 
        "firstAnimEnd":{
            "x": "center" ,
            "y": "center" 
        }, 
        "textSize2":"small-text",
        "text2": "Move X to End " ,
        "secondAnimEnd":{
            "x": "end" ,
            "y": "center" 
        }, 
        "timeToFade":"+=1"
    }
]
